whisper_mic/__init__.py
whisper_mic/cli.py
whisper_mic/utils.py
whisper_mic/whisper_mic.py
whisper_mic-1.4.4.dist-info/LICENSE
whisper_mic-1.4.4.dist-info/METADATA
whisper_mic-1.4.4.dist-info/WHEEL
whisper_mic-1.4.4.dist-info/entry_points.txt
whisper_mic-1.4.4.dist-info/top_level.txt
whisper_mic-1.4.4.dist-info/RECORD
