Metadata-Version: 2.1
Name: whisper_mic
Version: 1.4.4
Summary: Whisper for your microphone
Author-email: Blake Mallory <blakecmallory@gmail.com>
Classifier: Programming Language :: Python :: 3
Classifier: License :: OSI Approved :: MIT License
Classifier: Operating System :: OS Independent
Requires-Python: >=3.9
License-File: LICENSE
Requires-Dist: attrs
Requires-Dist: click
Requires-Dist: ffmpeg-python
Requires-Dist: more-itertools
Requires-Dist: numpy
Requires-Dist: openai-whisper
Requires-Dist: pyaudio
Requires-Dist: pydantic
Requires-Dist: pydub
Requires-Dist: pynput
Requires-Dist: requests
Requires-Dist: rich
Requires-Dist: speechrecognition
Requires-Dist: tdqm
Requires-Dist: torch
Requires-Dist: transformers
Requires-Dist: importlib-metadata ; python_version > "3.9"
